ord_schema/__init__.py
ord_schema/frozen_message.py
ord_schema/frozen_message_test.py
ord_schema/logging.py
ord_schema/message_helpers.py
ord_schema/message_helpers_test.py
ord_schema/resolvers.py
ord_schema/resolvers_test.py
ord_schema/templating.py
ord_schema/templating_test.py
ord_schema/units.py
ord_schema/units_test.py
ord_schema/updates.py
ord_schema/updates_test.py
ord_schema/validations.py
ord_schema/validations_test.py
ord_schema/macros/__init__.py
ord_schema/macros/solutions.py
ord_schema/macros/solutions_test.py
ord_schema/macros/workups.py
ord_schema/orm/__init__.py
ord_schema/orm/conftest.py
ord_schema/orm/database.py
ord_schema/orm/database_test.py
ord_schema/orm/mappers.py
ord_schema/orm/mappers_test.py
ord_schema/orm/rdkit_mappers.py
ord_schema/orm/rdkit_mappers_test.py
ord_schema/orm/scripts/__init__.py
ord_schema/orm/scripts/add_datasets.py
ord_schema/orm/scripts/add_datasets_test.py
ord_schema/proto/__init__.py
ord_schema/proto/dataset_pb2.py
ord_schema/proto/dataset_pb2.pyi
ord_schema/proto/dataset_pb2_test.py
ord_schema/proto/reaction_pb2.py
ord_schema/proto/reaction_pb2.pyi
ord_schema/proto/reaction_pb2_test.py
ord_schema/proto/test_pb2.py
ord_schema/proto/test_pb2.pyi
ord_schema/scripts/__init__.py
ord_schema/scripts/build_dataset.py
ord_schema/scripts/build_dataset_test.py
ord_schema/scripts/check_pb.py
ord_schema/scripts/check_pb_test.py
ord_schema/scripts/enumerate_dataset.py
ord_schema/scripts/enumerate_dataset_test.py
ord_schema/scripts/parse_uspto.py
ord_schema/scripts/process_dataset.py
ord_schema/scripts/process_dataset_test.py
ord_schema/scripts/validate_dataset.py
ord_schema/scripts/validate_dataset_test.py
ord_schema-0.3.99.dist-info/licenses/AUTHORS
ord_schema-0.3.99.dist-info/licenses/LICENSE
ord_schema-0.3.99.dist-info/METADATA
ord_schema-0.3.99.dist-info/WHEEL
ord_schema-0.3.99.dist-info/top_level.txt
ord_schema-0.3.99.dist-info/RECORD
