Metadata-Version: 2.4
Name: ord-schema
Version: 0.3.99
Summary: Schema for the Open Reaction Database
Home-page: https://github.com/Open-Reaction-Database/ord-schema
Classifier: Programming Language :: Python :: 3
Classifier: License :: OSI Approved :: Apache Software License
Classifier: Operating System :: OS Independent
Requires-Python: >=3.10
License-File: LICENSE
License-File: AUTHORS
Requires-Dist: Werkzeug>=3.0.3
Requires-Dist: docopt>=0.6.2
Requires-Dist: inflection>=0.5.1
Requires-Dist: joblib>=1.0.0
Requires-Dist: numpy>=1.26.4
Requires-Dist: openpyxl>=3.0.5
Requires-Dist: pandas>=1.0.4
Requires-Dist: protobuf<5,>=4.22.3
Requires-Dist: psycopg[binary,pool]>=3
Requires-Dist: pygithub>=1.51
Requires-Dist: python-dateutil>=1.10.0
Requires-Dist: rdkit>=2021.9.5
Requires-Dist: sqlalchemy>=2
Requires-Dist: tqdm>=4.61.2
Provides-Extra: docs
Requires-Dist: Pygments>=2.13.0; extra == "docs"
Requires-Dist: Sphinx>=5.3.0; extra == "docs"
Requires-Dist: ipython>=8.4.0; extra == "docs"
Requires-Dist: sphinx-rtd-theme>=1.1.1; extra == "docs"
Requires-Dist: sphinx-tabs>=3.4.0; extra == "docs"
Provides-Extra: examples
Requires-Dist: glob2>=0.7; extra == "examples"
Requires-Dist: matplotlib>=3.3.4; extra == "examples"
Requires-Dist: scikit-learn>=0.24.1; extra == "examples"
Requires-Dist: tensorflow>=2.4.1; extra == "examples"
Requires-Dist: wget>=3.2; extra == "examples"
Provides-Extra: tests
Requires-Dist: black[jupyter]>=22.3.0; extra == "tests"
Requires-Dist: coverage>=5.2.1; extra == "tests"
Requires-Dist: pylint>=2.17.4; extra == "tests"
Requires-Dist: pytest>=7.1.1; extra == "tests"
Requires-Dist: pytest-cov>=3.0.0; extra == "tests"
Requires-Dist: pytest-xdist>=3.0.2; extra == "tests"
Requires-Dist: pytype>=2023.6.16; extra == "tests"
Requires-Dist: testing-postgresql>=1.3.0; extra == "tests"
Requires-Dist: treon>=0.1.3; extra == "tests"
Dynamic: classifier
Dynamic: description
Dynamic: description-content-type
Dynamic: home-page
Dynamic: license-file
Dynamic: provides-extra
Dynamic: requires-dist
Dynamic: requires-python
Dynamic: summary
